torch_mice/__init__.py
torch_mice/affine_norm.py
torch_mice/atlas_projector.py
torch_mice/batched_icnn.py
torch_mice/convex_embed.py
torch_mice/convex_gate.py
torch_mice/convex_hash.py
torch_mice/positive_linear.py
torch_mice/vector_hull.py
torch_mice-0.5.0.dist-info/licenses/LICENSE.txt
torch_mice-0.5.0.dist-info/METADATA
torch_mice-0.5.0.dist-info/WHEEL
torch_mice-0.5.0.dist-info/top_level.txt
torch_mice-0.5.0.dist-info/RECORD
