Metadata-Version: 2.4
Name: torch-mice
Version: 0.5.0
Summary: Mixture of Convex Experts (MiCE) for PyTorch
Author-email: Joshuah Rainstar <Joshuah.Rainstar@gmail.com>
License: Copyright (c)  Joshuah Rainstar Joshuah.rainstar@gmail.com 2025
Project-URL: Homepage, https://github.com/falseywinchnet/MiCE
Project-URL: Repository, https://github.com/falseywinchnet/MiCE
Keywords: convex,mixture-of-experts,pytorch,icnn,machine-learning
Classifier: Programming Language :: Python :: 3
Classifier: License :: Other/Proprietary License
Classifier: Operating System :: OS Independent
Requires-Python: >=3.7
License-File: LICENSE.txt
Requires-Dist: torch>=1.6.0
Dynamic: license-file
